setup.py
pysensu/__init__.py
pysensu/pysensu.py
pysensu.egg-info/PKG-INFO
pysensu.egg-info/SOURCES.txt
pysensu.egg-info/dependency_links.txt
pysensu.egg-info/requires.txt
pysensu.egg-info/top_level.txt