Metadata-Version: 1.0
Name: pysensu
Version: 0.5
Summary: Utilities for working with Sensu
Home-page: https://github.com/kdaniels/pysensu
Author: Katherine Daniels
Author-email: kd@gc.io
License: UNKNOWN
Platform: UNKNOWN
